visual_kinematics/Frame.py
visual_kinematics/Robot.py
visual_kinematics/RobotDelta.py
visual_kinematics/RobotSerial.py
visual_kinematics/RobotTrajectory.py
visual_kinematics/__init__.py
visual_kinematics/utility.py
visual_kinematics-0.2.1.dist-info/LICENSE.txt
visual_kinematics-0.2.1.dist-info/METADATA
visual_kinematics-0.2.1.dist-info/WHEEL
visual_kinematics-0.2.1.dist-info/top_level.txt
visual_kinematics-0.2.1.dist-info/RECORD
