Metadata-Version: 2.1
Name: visual_kinematics
Version: 0.2.1
Summary: A package for calculating robot kinematics and visualizing trajectory
Home-page: https://github.com/dbddqy/visual_kinematics
Author: Yue QI
Author-email: dbddqy@outlook.com
License: UNKNOWN
Keywords: robotics, kinematics,inverse kinematics,trajectory planning,visualization
Platform: UNKNOWN
Classifier: Programming Language :: Python :: 3
Classifier: License :: OSI Approved :: MIT License
Classifier: Operating System :: OS Independent
Requires-Python: >=3.5
